cbers4asat/__init__.py
cbers4asat/cbers4asat.py
cbers4asat/cbers4a/__init__.py
cbers4asat/cbers4a/collections.py
cbers4asat/cbers4a/download.py
cbers4asat/cbers4a/item.py
cbers4asat/cbers4a/itemCollection.py
cbers4asat/cbers4a/request.py
cbers4asat/cbers4a/search.py
cbers4asat/cbers4a/utils/__init__.py
cbers4asat/cbers4a/utils/dataclass.py
cbers4asat/tools/__init__.py
cbers4asat/tools/geometry.py
cbers4asat/tools/grid.py
cbers4asat/tools/image.py
cbers4asat-0.10.0.dist-info/METADATA
cbers4asat-0.10.0.dist-info/WHEEL
cbers4asat-0.10.0.dist-info/licenses/LICENSE
cbers4asat-0.10.0.dist-info/RECORD
