Metadata-Version: 2.4
Name: cbers4asat
Version: 0.10.0
Summary: Biblioteca Python para realizar a busca e processamento de imagens dos satélites CBERS-04A e AMAZONIA-1
Project-URL: Homepage, https://cbers4asat.readthedocs.io/pt_BR/latest
Project-URL: Bug Tracker, https://github.com/gabriel-russo/cbers4asat/issues
Project-URL: Repository, https://github.com/gabriel-russo/cbers4asat.git
Author-email: Gabriel Russo <gabrielrusso@protonmail.com>
License: MIT License
License-File: LICENSE
Keywords: amazonia-1,cbers,cbers-04a,cbers-4a,cbers4a,geoprocessing,remote sensing
Classifier: License :: OSI Approved :: MIT License
Classifier: Operating System :: OS Independent
Classifier: Programming Language :: Python :: 3.11
Classifier: Programming Language :: Python :: 3.12
Classifier: Programming Language :: Python :: 3.13
Classifier: Topic :: Scientific/Engineering :: GIS
Requires-Python: <4,>=3.11
Requires-Dist: geopandas>=1.1.1
Requires-Dist: requests>=2.32.5
Provides-Extra: dev
Requires-Dist: hatch>=1.14.2; extra == 'dev'
Provides-Extra: tools
Requires-Dist: geojson>=3.2.0; extra == 'tools'
Requires-Dist: geomet>=1.1.0; extra == 'tools'
Requires-Dist: numpy>=2.3.3; extra == 'tools'
Requires-Dist: rasterio>=1.4.3; extra == 'tools'
Requires-Dist: scikit-image>=0.25.2; extra == 'tools'
